MANIFEST.in
README.rst
setup.py
blanc_basic_news/__init__.py
blanc_basic_news/admin.py
blanc_basic_news/apps.py
blanc_basic_news/feeds.py
blanc_basic_news/models.py
blanc_basic_news/tests.py
blanc_basic_news/urls.py
blanc_basic_news/views.py
blanc_basic_news.egg-info/PKG-INFO
blanc_basic_news.egg-info/SOURCES.txt
blanc_basic_news.egg-info/dependency_links.txt
blanc_basic_news.egg-info/requires.txt
blanc_basic_news.egg-info/top_level.txt
blanc_basic_news/migrations/0001_initial.py
blanc_basic_news/migrations/0002_post_url.py
blanc_basic_news/migrations/__init__.py
blanc_basic_news/templatetags/__init__.py
blanc_basic_news/templatetags/news_tags.py