Metadata-Version: 1.1
Name: blanc-basic-news
Version: 0.3.2
Summary: Blanc Basic News for Django
Home-page: https://github.com/blancltd/blanc-basic-news
Author: Blanc Ltd
Author-email: studio@blanc.ltd.uk
License: BSD
Platform: any
Classifier: Environment :: Web Environment
Classifier: Framework :: Django
Classifier: License :: OSI Approved :: BSD License
Classifier: Operating System :: OS Independent
Classifier: Programming Language :: Python
Classifier: Programming Language :: Python :: 2
Classifier: Programming Language :: Python :: 2.7
Classifier: Programming Language :: Python :: 3
Classifier: Programming Language :: Python :: 3.2
Classifier: Programming Language :: Python :: 3.3
Classifier: Programming Language :: Python :: 3.4
